database/__init__.py
database/database.py
fuzzy_markov_logic_network/__init__.py
fuzzy_markov_logic_network/is_a_generator.py
fuzzy_markov_logic_network/word_net.py
ground_atom/__init__.py
ground_atom/ground_atom.py
high_level_markov_logic_network/__init__.py
high_level_markov_logic_network/database.py
high_level_markov_logic_network/ground_atom.py
high_level_markov_logic_network/markov_logic_network.py
high_level_markov_logic_network/fuzzy_markov_logic_network/__init__.py
high_level_markov_logic_network/fuzzy_markov_logic_network/is_a_generator.py
high_level_markov_logic_network/fuzzy_markov_logic_network/word_net.py
high_level_markov_logic_network/test/__init__.py
high_level_markov_logic_network/test/database/__init__.py
high_level_markov_logic_network/test/fuzzy_markov_logic_network_test/__init__.py
high_level_markov_logic_network/test/fuzzy_markov_logic_network_test/is_a_generator_test.py
high_level_markov_logic_network/test/ground_atom/__init__.py
high_level_markov_logic_network/test/ground_atom/ground_atom_test.py
high_level_markov_logic_network/test/markov_logic_network/__init__.py
high_level_markov_logic_network/test/markov_logic_network/markov_logic_network_test.py
markov_logic_network/__init__.py
markov_logic_network/markov_logic_network.py
test/__init__.py
test/database/__init__.py
test/fuzzy_markov_logic_network_test/__init__.py
test/fuzzy_markov_logic_network_test/is_a_generator_test.py
test/ground_atom/__init__.py
test/ground_atom/ground_atom_test.py
test/markov_logic_network/__init__.py
test/markov_logic_network/markov_logic_network_test.py
high_level_markov_logic_network-1.0.1.dist-info/LICENSE
high_level_markov_logic_network-1.0.1.dist-info/METADATA
high_level_markov_logic_network-1.0.1.dist-info/WHEEL
high_level_markov_logic_network-1.0.1.dist-info/top_level.txt
high_level_markov_logic_network-1.0.1.dist-info/RECORD
