Metadata-Version: 2.1
Name: high-level-markov-logic-network
Version: 1.0.1
Summary: Provides high level functions to access the main functionality of pracmln.
Home-page: https://github.com/code-iai/high-level-markov-logic-network
Author: Sebastian Koralewski
Author-email: seba@cs.uni-bremen.de
License: UNKNOWN
Platform: UNKNOWN
Classifier: Programming Language :: Python :: 2
Classifier: License :: OSI Approved :: MIT License
Classifier: Operating System :: OS Independent
Requires-Dist: pracmln (==1.2.3)
